parse_apple_health_data/__init__.py
parse_apple_health_data/parser.py
parse_apple_health_data/utils.py
parse_apple_health_data-1.0.0.dist-info/LICENSE
parse_apple_health_data-1.0.0.dist-info/METADATA
parse_apple_health_data-1.0.0.dist-info/WHEEL
parse_apple_health_data-1.0.0.dist-info/top_level.txt
parse_apple_health_data-1.0.0.dist-info/RECORD
