Metadata-Version: 2.2
Name: parse_apple_health_data
Version: 1.0.0
Summary: A Python package for parsing Apple Health Export data
Home-page: https://github.com/soomelauri/parse_apple_health_data
Author: Lauri Soome
Author-email: Lauri Soome <las623@lehigh.edu>
Project-URL: Homepage, https://github.com/soomelauri/parse_apple_health_data
Project-URL: Bug Tracker, https://github.com/soomelauri/parse_apple_health_data/issues
Classifier: Programming Language :: Python :: 3
Classifier: License :: OSI Approved :: MIT License
Classifier: Operating System :: OS Independent
Requires-Python: >=3.8
License-File: LICENSE
Requires-Dist: pandas>=1.0.0
